messagingclient/__init__.py
messagingclient/client.py
messagingclient-0.3.0.dist-info/licenses/LICENSE
messagingclient-0.3.0.dist-info/METADATA
messagingclient-0.3.0.dist-info/WHEEL
messagingclient-0.3.0.dist-info/top_level.txt
messagingclient-0.3.0.dist-info/RECORD
