Metadata-Version: 2.4
Name: messagingclient
Version: 0.3.0
Summary: Messaging Client
Home-page: https://github.com/seung-lab/messaging-client
Author: Akhilesh Halageri
Project-URL: Bug Tracker, https://github.com/seung-lab/messaging-client/issues
Classifier: Programming Language :: Python :: 3
Classifier: License :: OSI Approved :: MIT License
Classifier: Operating System :: OS Independent
Requires-Python: >=3.6
License-File: LICENSE
Requires-Dist: numpy
Requires-Dist: google-cloud-pubsub
Dynamic: author
Dynamic: classifier
Dynamic: description
Dynamic: description-content-type
Dynamic: home-page
Dynamic: license-file
Dynamic: project-url
Dynamic: requires-dist
Dynamic: requires-python
Dynamic: summary
